Metadata-Version: 2.1
Name: pyrelvis
Version: 0.0.3
Summary: Pyrelvis is a simple binary relation visualizer
Home-page: https://github.com/RobinSeidel/pyrelvis
Author: Robin Seidel
Author-email: robin.seidel@tum.de
License: MIT
Download-URL: https://github.com/RobinSeidel/pyrelvis/archive/refs/tags/v0.0.1.tar.gz
Keywords: relation,binary,visualizer,svg
Platform: UNKNOWN
Classifier: Development Status :: 3 - Alpha
Classifier: Intended Audience :: Developers
Classifier: License :: OSI Approved :: MIT License
Classifier: Programming Language :: Python :: 3
License-File: LICENSE
